README.md
setup.py
MoonshotAI_Api/LICENSE
MoonshotAI_Api/README.md
MoonshotAI_Api/__init__.py
MoonshotAI_Api/ltv_client.py
MoonshotAI_Api.egg-info/PKG-INFO
MoonshotAI_Api.egg-info/SOURCES.txt
MoonshotAI_Api.egg-info/dependency_links.txt
MoonshotAI_Api.egg-info/not-zip-safe
MoonshotAI_Api.egg-info/requires.txt
MoonshotAI_Api.egg-info/top_level.txt
MoonshotAI_Api/utils/consts.py
MoonshotAI_Api/utils/output_enum.py
MoonshotAI_Api/utils/utils.py
Moonshotai_api.egg-info/PKG-INFO
Moonshotai_api.egg-info/SOURCES.txt
Moonshotai_api.egg-info/dependency_links.txt
Moonshotai_api.egg-info/not-zip-safe
Moonshotai_api.egg-info/requires.txt
Moonshotai_api.egg-info/top_level.txt
moonshotai_api.egg-info/PKG-INFO
moonshotai_api.egg-info/SOURCES.txt
moonshotai_api.egg-info/dependency_links.txt
moonshotai_api.egg-info/not-zip-safe
moonshotai_api.egg-info/requires.txt
moonshotai_api.egg-info/top_level.txt