Metadata-Version: 1.0
Name: moonshotai-api
Version: 0.0.5
Summary: LTV API SDK
Home-page: UNKNOWN
Author: Tomer Efr
Author-email: UNKNOWN
License: MIT
Platform: UNKNOWN
